{
    "accounts_options":[
        {
            "id": "MAILBOX_MAIN",
            "url" : "https://pluton2.centrum24.pl/centrum24-web/native/mailbox",
            "isAvailable": true,
            "method": "POST",
            "isFullScreen": true
        },
        {
            "id": "ADD_BANKS",
            "url": "https://micrositeoneapp2.santanderbankpolska.pl/centrum24-web/native/ps-aggregator",
            "isAvailable": true,
            "method": "GET"
        },
        {
            "id": "CHANGE_ACCOUNT",
            "url": "https://micrositeoneapp2.santanderbankpolska.pl/centrum24-web/native/tiles#/contact-form",
            "isAvailable": true,
            "method": "GET",
            "isFullScreen": true
        },
        {
            "id": "EDIT_GOAL",
            "url": "https://micrositeoneapp2.santanderbankpolska.pl/centrum24-web/native/savings-goals#/goal/{{NUMBER}}",
            "isAvailable": true,
            "method": "GET"
        },
        {
            "id":"ALERTS_24",
            "url": "https://micrositeoneapp2.santanderbankpolska.pl/centrum24-web/native/notification-settings",
            "isAvailable": true,
            "method": "GET"
        },
        {
            "id":"GENERATE_QR",
            "url": null,
            "isAvailable": false,
            "method": "GET"
        },
        {
            "id":"CREDIT_CARD_REPAYMENT",
            "url": null,
            "isAvailable": false,
            "method": "GET"
        },
        {
            "id": "HISTORY",
            "url": null,
            "isAvailable": false,
            "method": "GET"
        },
        {
            "id": "VIEW_STATEMENTS",
            "url": "https://micrositeoneapp2.santanderbankpolska.pl/centrum24-web/native/mailbox#/mailbox/threads/inbox;page=1;messageType=ewyciagi",
            "isAvailable": true,
            "method": "GET"
        },
        {
            "id": "CUSTOMER_SERVICE",
            "url": "https://micrositeoneapp2.santanderbankpolska.pl/centrum24-web/native/customer-service",
            "isAvailable": true,
            "method": "GET"
        },
        {
            "id": "OPEN_DEPOSIT",
            "url": null,
            "isAvailable": false,
            "method": "GET"
        },
        {
            "id": "FX_EXCHANGE",
            "url": "https://micrositeoneapp2.santanderbankpolska.pl/centrum24-web/native/kantor",
            "isAvailable": true,
            "method": "POST"
        },
        {
            "id": "MEMBER_GET_MEMBER",
            "isAvailable": true,
            "method": "POST",
            "isFullScreen": true,
            "url": "https://micrositeoneapp2.santanderbankpolska.pl/centrum24-web/native/mgm"
        },
        {
            "id": "SAVING_GOALS",
            "url": "https://micrositeoneapp2.santanderbankpolska.pl/centrum24-web/native/savings-goals#/start-saving",
            "isAvailable": true,
            "method": "POST"
        }
    ],
    
    "cards_options" : [
        {
            "id": "MULTICURRENCY",
            "url" : "https://micrositeoneapp2.santanderbankpolska.pl/centrum24-web/native/tiles#/multiCurrencyCard/{$VPAN}",
            "isAvailable": true,
            "method": "POST"
        },
        {
            "id": "CANCEL_CARD",
            "url" : "https://micrositeoneapp2.santanderbankpolska.pl/centrum24-mobile-web/cards#/app/cards_restriction_reasons/{$VPAN}",
            "isAvailable": true,
            "method": "POST"
        },
        {
            "id": "CARD_CREDIT_LIMIT_INCREASE",
            "url" : "https://micrositeoneapp2.santanderbankpolska.pl/centrum24-web/native/new-bbc-offer#/pages/product-details/increaseCreditCardLimit",
            "isAvailable": true,
            "method": "POST",
            "isFullScreen": true
        }
    ],
    "help_center_options" : [
        {
            "id": "YOUR_AFFAIRS",
            "url" : "https://micrositeoneapp2.santanderbankpolska.pl/centrum24-web/native/customer-service",
            "isAvailable": true,
            "method": "POST",
            "isFullScreen": true
        },
        {
            "id": "MAILBOX",
            "url" : "https://micrositeoneapp2.santanderbankpolska.pl/centrum24-web/native/mailbox#/mailbox/newMessage;fresh=true",
            "isAvailable": true,
            "method": "POST",
            "isFullScreen": true
        }
    ],
    "insurance_options" : [
        {
            "id": "PROTECTION_INSURANCE",
            "url" : "https://micrositeoneapp2.santanderbankpolska.pl/omni/oneapp{$INSURANCE_URL}",
            "isAvailable": true,
            "method": "POST",
            "isFullScreen": true
        }
    ]
}
